{
    "gelDesktop": {
        "prefix": "gel.",
        "files": [
            {
                "type": "spritesheet",
                "key": "achievements",
                "url": "gel/achievements.png",
                "frameConfig": {
                    "frameWidth": 248,
                    "frameHeight": 64,
                    "frameMax": 2,
                    "margin": 0,
                    "spacing": 4
                }
            },
            {
                "type": "spritesheet",
                "key": "achievements-small",
                "url": "gel/achievements-small.png",
                "frameConfig": {
                    "frameWidth": 64,
                    "frameHeight": 64,
                    "frameMax": 2,
                    "margin": 0,
                    "spacing": 4
                }
            },
            {
                "type": "image",
                "key": "notification",
                "url": "gel/notification.png"
            },
            {
                "type": "spritesheet",
                "key": "play",
                "url": "gel/play.png",
                "frameConfig": {
                    "frameWidth": 180,
                    "frameHeight": 180,
                    "frameMax": 2,
                    "margin": 0,
                    "spacing": 4
                }
            },
            {
                "type": "spritesheet",
                "key": "exit",
                "url": "gel/exit.png",
                "frameConfig": {
                    "frameWidth": 64,
                    "frameHeight": 64,
                    "frameMax": 2,
                    "margin": 0,
                    "spacing": 4
                }
            },
            {
                "type": "spritesheet",
                "key": "how-to-play",
                "url": "gel/how-to-play.png",
                "frameConfig": {
                    "frameWidth": 248,
                    "frameHeight": 64,
                    "frameMax": 2,
                    "margin": 0,
                    "spacing": 4
                }
            },
            {
                "type": "spritesheet",
                "key": "settings",
                "url": "gel/settings.png",
                "frameConfig": {
                    "frameWidth": 64,
                    "frameHeight": 64,
                    "frameMax": 2,
                    "margin": 0,
                    "spacing": 4
                }
            },
            {
                "type": "spritesheet",
                "key": "home",
                "url": "gel/home.png",
                "frameConfig": {
                    "frameWidth": 64,
                    "frameHeight": 64,
                    "frameMax": 2,
                    "margin": 0,
                    "spacing": 4
                }
            },
            {
                "type": "spritesheet",
                "key": "back",
                "url": "gel/back.png",
                "frameConfig": {
                    "frameWidth": 64,
                    "frameHeight": 64,
                    "frameMax": 2,
                    "margin": 0,
                    "spacing": 4
                }
            },
            {
                "type": "spritesheet",
                "key": "audio-on",
                "url": "gel/audio-on.png",
                "frameConfig": {
                    "frameWidth": 64,
                    "frameHeight": 64,
                    "frameMax": 2,
                    "margin": 0,
                    "spacing": 4
                }
            },
            {
                "type": "spritesheet",
                "key": "audio-off",
                "url": "gel/audio-off.png",
                "frameConfig": {
                    "frameWidth": 64,
                    "frameHeight": 64,
                    "frameMax": 2,
                    "margin": 0,
                    "spacing": 4
                }
            },
            {
                "type": "spritesheet",
                "key": "pause",
                "url": "gel/pause.png",
                "frameConfig": {
                    "frameWidth": 64,
                    "frameHeight": 64,
                    "frameMax": 2,
                    "margin": 0,
                    "spacing": 4
                }
            },
            {
                "type": "spritesheet",
                "key": "skip",
                "url": "gel/skip.png",
                "frameConfig": {
                    "frameWidth": 64,
                    "frameHeight": 64,
                    "frameMax": 2,
                    "margin": 0,
                    "spacing": 4
                }
            },
            {
                "type": "spritesheet",
                "key": "continue",
                "url": "gel/continue.png",
                "frameConfig": {
                    "frameWidth": 224,
                    "frameHeight": 64,
                    "frameMax": 2,
                    "margin": 0,
                    "spacing": 4
                }
            },
            {
                "type": "spritesheet",
                "key": "restart",
                "url": "gel/restart.png",
                "frameConfig": {
                    "frameWidth": 224,
                    "frameHeight": 64,
                    "frameMax": 2,
                    "margin": 0,
                    "spacing": 4
                }
            },
            {
                "type": "spritesheet",
                "key": "play-again",
                "url": "gel/play-again.png",
                "frameConfig": {
                    "frameWidth": 224,
                    "frameHeight": 64,
                    "frameMax": 2,
                    "margin": 0,
                    "spacing": 4
                }
            },
            {
                "type": "spritesheet",
                "key": "previous",
                "url": "gel/previous.png",
                "frameConfig": {
                    "frameWidth": 64,
                    "frameHeight": 64,
                    "frameMax": 2,
                    "margin": 0,
                    "spacing": 4
                }
            },
            {
                "type": "spritesheet",
                "key": "next",
                "url": "gel/next.png",
                "frameConfig": {
                    "frameWidth": 64,
                    "frameHeight": 64,
                    "frameMax": 2,
                    "margin": 0,
                    "spacing": 4
                }
            },
            {
                "type": "spritesheet",
                "key": "replay",
                "url": "gel/replay.png",
                "frameConfig": {
                    "frameWidth": 120,
                    "frameHeight": 120,
                    "frameMax": 2,
                    "margin": 0,
                    "spacing": 4
                }
            },
            {
                "type": "spritesheet",
                "key": "levels",
                "url": "gel/levels.png",
                "frameConfig": {
                    "frameWidth": 120,
                    "frameHeight": 120,
                    "frameMax": 2,
                    "margin": 0,
                    "spacing": 4
                }
            },
            {
                "type": "image",
                "key": "audio-off-icon",
                "url": "gel/audio-off-icon.png"
            },
            {
                "type": "image",
                "key": "fx-off-icon",
                "url": "gel/fx-off-icon.png"
            }
        ]
    }
}
